Workbook

Sheet Cover
B3: EQUITY RESEARCH — FINANCIAL MODEL
I4: ='Discounted Cash Flow'!B31 -> 2430
B5: ASIAN PAINTS LIMITED
B6: NSE: ASIANPAINT | Consumer Durables — Paints | Nifty 50 | I6: ='Discounted Cash Flow'!B32 -> -0.754041
G10: ='Discounted Cash Flow'!B30 -> 597.68038

Sheet Assumptions
A1: ASIAN PAINTS
A2: Line Item | B2: FY2023 | C2: FY2024 | D2: FY2025E | E2: FY2026E | G2: =HYPERLINK("https://www.screener.in/company/ASIANPAINT/consolidated/", "Source: Screener") -> Source: Screener
A3: Revenue(in Crores) | B3: 34489 | C3: 35495 | D3: =C3*(1+D4) -> 37269.75 | E3: =D3*(1+E4) -> 39878.632
A4: Revenue Growth % | B4: 0.186 | C4: 0.029 | D4: 0.05 | E4: 0.07
A5: EBITDA Margin% | B5: 0.18 | C5: 0.21 | D5: 0.19 | E5: 0.19
A6: Tax Rate | B6: 0.26 | C6: 0.24 | D6: 0.26 | E6: 0.26
A7: D&A (Depriciation) (in Crores) | B7: 858 | C7: 853 | D7: 1026 | E7: 1100
A8: Capex (in Crores) | B8: 1282 | C8: 2548 | D8: 941 | E8: 1200
A9: Interest Expense (in Crores) | B9: 144 | C9: 205 | D9: 227 | E9: 230
A10: DSO(Debtor Days) | B10: 49 | C10: 50 | D10: 46 | E10: 46
A11: DIO(Inventory Days) | B11: 121 | C11: 122 | D11: 142 | E11: 135
A12: DPO(Payable Days) | B12: 71 | C12: 79 | D12: 81 | E12: 80
A13: Dividends (~60-65%) (in Crores) | B13: 2513 | C13: 3224 | D13: 2411 | E13: 2500
A17: COGS % - (what % of revenue goes to making the product)
A18: EBITDA Margin % - (operating profit generated before interest, taxes, depriciation & ammortization)
A19: Dividends - (A portion of a company’s profit distributed to shareholders)

Sheet Income Statement
A1: ASIAN PAINTS
A2: Line Item | B2: FY2023 | C2: FY2024 | D2: FY2025E | E2: FY2026E | G2: =HYPERLINK("https://www.screener.in/company/ASIANPAINT/consolidated/", "Source: Screener") -> Source: Screener
A3: Revenue(in Crores) | B3: =Assumptions!B3 -> 34489 | C3: =Assumptions!C3 -> 35495 | D3: =Assumptions!D3 -> 37269.75 | E3: =Assumptions!E3 -> 39878.632
A4: EBITDA (in Crores) | B4: =B3*Assumptions!B5 -> 6208.02 | C4: =C3*Assumptions!C5 -> 7453.95 | D4: =D3*Assumptions!D5 -> 7081.2525 | E4: =E3*Assumptions!E5 -> 7576.9402 | G4: Revenue * EBITDA Margin
A5: D&A (Depriciation) (in Crores) | B5: =Assumptions!B7 -> 858 | C5: =Assumptions!C7 -> 853 | D5: =Assumptions!D7 -> 1026 | E5: =Assumptions!E7 -> 1100
A6: EBIT (in Crores) | B6: =B4 - B5 -> 5350.02 | C6: =C4 - C5 -> 6600.95 | D6: =D4 - D5 -> 6055.2525 | E6: =E4 - E5 -> 6476.9402 | G6: EBITDA - D&A
A7: Interest Expense (in Crores) | B7: =Assumptions!B9 -> 144 | C7: =Assumptions!C9 -> 205 | D7: =Assumptions!D9 -> 227 | E7: =Assumptions!E9 -> 230
A8: EBT (Profit before Tax) | B8: =B6-B7 -> 5206.02 | C8: =C6-C7 -> 6395.95 | D8: =D6-D7 -> 5828.2525 | E8: =E6-E7 -> 6246.9402 | G8: EBIT - Interest Expense
A9: Tax | B9: =B8 *Assumptions!B6 -> 1353.5652 | C9: =C8 *Assumptions!C6 -> 1535.028 | D9: =D8 *Assumptions!D6 -> 1515.3457 | E9: =E8 *Assumptions!E6 -> 1624.2044 | G9: EBT * Tax Rate
A10: Net Income | B10: =B8-B9 -> 3852.4548 | C10: =C8-C9 -> 4860.922 | D10: =D8-D9 -> 4312.9069 | E10: =E8-E9 -> 4622.7357 | G10: EBT-Tax
A14: COGS % - (what % of revenue goes to making the product)
A15: EBITDA Margin % - (operating profit generated before interest, taxes, depriciation & ammortization)
A16: Dividends - (A portion of a company’s profit distributed to shareholders)

Sheet Balance Sheet
A1: ASIAN PAINTS
A2: Line Item | B2: FY2023 | C2: FY2024 | D2: FY2025E | E2: FY2026E | G2: =HYPERLINK("https://www.screener.in/company/ASIANPAINT/consolidated/", "Source: Screener") -> Source: Screener
A3: ASSETS
A4: Cash & Equivalents(in Crores) | B4: 3364 | C4: 3937 | D4: ='Cash Flow'!D19 -> 5599.9204 | E4: ='Cash Flow'!E19 -> 7335.577
A5: Accounts Receivable(in Crores) | B5: ='Income Statement'!B3*(Assumptions!B10/365) -> 4630.0301 | C5: ='Income Statement'!C3*(Assumptions!C10/365) -> 4862.3288 | D5: ='Income Statement'!D3*(Assumptions!D10/365) -> 4697.0096 | E5: ='Income Statement'!E3*(Assumptions!E10/365) -> 5025.8003
A6: Inventory(in Crores) | B6: ='Income Statement'!B4*(Assumptions!B11/365) -> 2058.0012 | C6: ='Income Statement'!C4*(Assumptions!C11/365) -> 2491.4573 | D6: ='Income Statement'!D4*(Assumptions!D11/365) -> 2754.8982 | E6: ='Income Statement'!E4*(Assumptions!E11/365) -> 2802.4299
A7: Fixed Assets(in Crores) | B7: 5770 | C7: 7147 | D7: =C7+Assumptions!D8-Assumptions!D7 -> 7062 | E7: =D7+Assumptions!E8-Assumptions!E7 -> 7162
A8: Total Assets (in Crores) | B8: =SUM(B4:B7) -> 15822.031 | C8: =SUM(C4:C7) -> 18437.786 | D8: =SUM(D4:D7) -> 20113.828 | E8: =SUM(E4:E7) -> 22325.807
A9: LIABILITIES & EQUITY SIDE
A10: Accounts Payable(in Crores) | B10: ='Income Statement'!B4*(Assumptions!B12/365) -> 1207.5875 | C10: ='Income Statement'!C4*(Assumptions!C12/365) -> 1613.3207 | D10: ='Income Statement'!D4*(Assumptions!D12/365) -> 1571.456 | E10: ='Income Statement'!E4*(Assumptions!E12/365) -> 1660.6992
A11: Borrowings (in Crores) | B11: 1933 | C11: 2474 | D11: 2290 | E11: 2290
A12: Share Capital | B12: 96 | C12: 96 | D12: =C12 -> 96 | E12: =D12 -> 96
A13: Retained Earnings(in Crores) | B13: 15896 | C13: 18632 | D13: =C13+'Income Statement'!D10-Assumptions!D13 -> 20533.907 | E13: =D13+'Income Statement'!E10-Assumptions!E13 -> 22656.643
A14: Total Liabilities & Equity | B14: =SUM(B10:B13) -> 19132.587 | C14: =SUM(C10:C13) -> 22815.321 | D14: =SUM(D10:D13) -> 24491.363 | E14: =SUM(E10:E13) -> 26703.342
A16: Check : Assets = Liabilities + Equity | B16: =B8 - B14 -> -3310.5562 | C16: =C8 - C14 -> -4377.5347 | D16: =D8 - D14 -> -4377.5347 | E16: =E8 - E14 -> -4377.5347
A19: COGS % - (what % of revenue goes to making the product)
A20: EBITDA Margin % - (operating profit generated before interest, taxes, depriciation & ammortization)
A21: Dividends - (A portion of a company’s profit distributed to shareholders)

Sheet Cash Flow
A1: ASIAN PAINTS
A2: Line Item | B2: FY2023 | C2: FY2024 | D2: FY2025E | E2: FY2026E | G2: =HYPERLINK("https://www.screener.in/company/ASIANPAINT/consolidated/", "Source: Screener") -> Source: Screener
A3: Operating Activities
A4: Net Income | B4: ='Income Statement'!B10 -> 3852.4548 | C4: ='Income Statement'!C10 -> 4860.922 | D4: ='Income Statement'!D10 -> 4312.9069 | E4: ='Income Statement'!E10 -> 4622.7357
A5: D&A | B5: ='Income Statement'!B5 -> 858 | C5: ='Income Statement'!C5 -> 853 | D5: ='Income Statement'!D5 -> 1026 | E5: ='Income Statement'!E5 -> 1100
A6: Change in Receivables | B6: 0 | C6: =-('Balance Sheet'!C5-'Balance Sheet'!B5) -> -232.29863 | D6: =-('Balance Sheet'!D5-'Balance Sheet'!C5) -> 165.31918 | E6: =-('Balance Sheet'!E5-'Balance Sheet'!D5) -> -328.79067
A7: Change in Inventory | B7: 0 | C7: =-('Balance Sheet'!C6-'Balance Sheet'!B6) -> -433.45611 | D7: =-('Balance Sheet'!D6-'Balance Sheet'!C6) -> -263.44097 | E7: =-('Balance Sheet'!E6-'Balance Sheet'!D6) -> -47.531695
A8: Change in Payables | B8: 0 | C8: =('Balance Sheet'!C10-'Balance Sheet'!B10) -> 405.73323 | D8: =('Balance Sheet'!D10-'Balance Sheet'!C10) -> -41.864651 | E8: =('Balance Sheet'!E10-'Balance Sheet'!D10) -> 89.243182
A9: Cash from operations (CFO) | B9: =SUM(B4:B8) -> 4710.4548 | C9: =SUM(C4:C8) -> 5453.9005 | D9: =SUM(D4:D8) -> 5198.9204 | E9: =SUM(E4:E8) -> 5435.6565
A10: Investing Activities
A11: Capex | B11: =-Assumptions!B8 -> -1282 | C11: =-Assumptions!C8 -> -2548 | D11: =-Assumptions!D8 -> -941 | E11: =-Assumptions!E8 -> -1200
A12: Cash from investing (CFI) | B12: =B11 -> -1282 | C12: =C11 -> -2548 | D12: =D11 -> -941 | E12: =E11 -> -1200
A13: Financial Activities
A14: Change in Debt | B14: 0 | C14: ='Balance Sheet'!C11-'Balance Sheet'!B11 -> 541 | D14: ='Balance Sheet'!D11-'Balance Sheet'!C11 -> -184 | E14: ='Balance Sheet'!E11-'Balance Sheet'!D11 -> 0
A15: Dividends Paid | B15: =-Assumptions!B13 -> -2513 | C15: =-Assumptions!C13 -> -3224 | D15: =-Assumptions!D13 -> -2411 | E15: =-Assumptions!E13 -> -2500
A16: Cash from Financing (CFF) | B16: =SUM(B14:B15) -> -2513 | C16: =SUM(C14:C15) -> -2683 | D16: =SUM(D14:D15) -> -2595 | E16: =SUM(E14:E15) -> -2500
A17: Net Change in Cash | B17: =SUM(B9,B12,B16) -> 915.4548 | C17: =SUM(C9,C12,C16) -> 222.90049 | D17: =SUM(D9,D12,D16) -> 1662.9204 | E17: =SUM(E9,E12,E16) -> 1735.6565
A18: Opening Cash | B18: 3364 | C18: ='Balance Sheet'!B4 -> 3364 | D18: ='Balance Sheet'!C4 -> 3937 | E18: ='Balance Sheet'!D4 -> 5599.9204
A19: Closing Cash | B19: =SUM(B17:B18) -> 4279.4548 | C19: =SUM(C17:C18) -> 3586.9005 | D19: =SUM(D17:D18) -> 5599.9204 | E19: =SUM(E17:E18) -> 7335.577
A21: Check: Ending Cash = Balance Sheet Cash | B21: ='Balance Sheet'!B4-'Cash Flow'!B19 -> -915.4548 | C21: ='Balance Sheet'!C4-'Cash Flow'!C19 -> 350.09951 | D21: ='Balance Sheet'!D4-'Cash Flow'!D19 -> 0 | E21: ='Balance Sheet'!E4-'Cash Flow'!E19 -> 0
A23: COGS % - (what % of revenue goes to making the product)
A24: EBITDA Margin % - (operating profit generated before interest, taxes, depriciation & ammortization)
A25: Dividends - (A portion of a company’s profit distributed to shareholders)

Sheet Discounted Cash Flow
A1: ASIAN PAINTS
A2: DCF Assumptions | B2: -
A3: Weighted average cost of capital (WACC)/Discount Rate | B3: =Sensitivity!I2 -> 0.12
A4: Terminal growth rate | B4: =Sensitivity!I3 -> 0.04
A5: Projection Years | B5: 5
A6: Shares Outstanding (in Crores) | B6: 95.92
A7: Current Market Price (in Crores) | B7: 2430
A8: Net Debt (in Crores) | B8: 947
A9: Driver | B9: FY2024 | C9: FY2025E | D9: FY2026E | E9: FY2027E | F9: FY2028E
A10: Revenue | B10: =Assumptions!C3 -> 35495 | C10: =Assumptions!D3 -> 37269.75 | D10: =Assumptions!E3 -> 39878.632 | E10: =D10*(1+0.07) -> 42670.137 | F10: =E10*(1+0.06) -> 45230.345 | H10: Assuming 7% then 6% growth as Asian Paints matures
A11: EBITDA | B11: =Assumptions!C5*'Discounted Cash Flow'!B10 -> 7453.95 | C11: =Assumptions!D5*'Discounted Cash Flow'!C10 -> 7081.2525 | D11: =Assumptions!E5*'Discounted Cash Flow'!D10 -> 7576.9402 | E11: =E10*0.19 -> 8107.326 | F11: =F10*0.19 -> 8593.7655
A12: D&A | B12: =Assumptions!C7 -> 853 | C12: =Assumptions!D7 -> 1026 | D12: =Assumptions!E7 -> 1100 | E12: 1150 | F12: 1200
A13: EBITDA | B13: =B11-B12 -> 6600.95 | C13: =C11-C12 -> 6055.2525 | D13: =D11-D12 -> 6476.9402 | E13: =E11-E12 -> 6957.326 | F13: =F11-F12 -> 7393.7655
A14: Tax on EBIT | B14: =B13*Assumptions!C6 -> 1584.228 | C14: =C13*Assumptions!D6 -> 1574.3657 | D14: =D13*Assumptions!E6 -> 1684.0044 | E14: =E13*0.26 -> 1808.9048 | F14: =F13*0.26 -> 1922.379
A15: Capex | B15: =- Assumptions!C8 -> -2548 | C15: =- Assumptions!D8 -> -941 | D15: =- Assumptions!E8 -> -1200 | E15: -1300 | F15: -1400
A16: Free Cash Flow to Firm (FCFF) | B16: =B13-B14+B12+B15 -> 3321.722 | C16: =C13-C14+C12+C15 -> 4565.8869 | D16: =D13-D14+D12+D15 -> 4692.9357 | E16: =E13-E14+E12+E15 -> 4998.4212 | F16: =F13-F14+F12+F15 -> 5271.3865 | H16: FCFF = EBIT - Tax on EBIT + D&A - Capex
A17: Year Number | B17: 0 | C17: 1 | D17: 2 | E17: 3 | F17: 4
A18: Discount Factor | B18: =1/((1+$B$3)^B17) -> 1 | C18: =1/((1+$B$3)^C17) -> 0.89285714 | D18: =1/((1+$B$3)^D17) -> 0.79719388 | E18: =1/((1+$B$3)^E17) -> 0.71178025 | F18: =1/((1+$B$3)^F17) -> 0.63551808 | H18: Discount Factor = 1/(1+WACC)^Year Number
A19: Discounted FCFF (in Crores) | B19: =B16*B18 -> 3321.722 | C19: =C16*C18 -> 4076.6847 | D19: =D16*D18 -> 3741.1796 | E19: =E16*E18 -> 3557.7775 | F19: =F16*F18 -> 3350.0614
A21: Terminal Value (in Crores) | B21: =F16*(1+$B$4)/($B$3 - $B$4) -> 68528.025
A22: Discounted Terminal Value (in Crores) | B22: =B21*F18 -> 43550.798
A24: Sum of Discounted FCFF (in Crores) | B24: =SUM(C19:F19) -> 14725.703
A25: Discounted Terminal Value (in Crores) | B25: =B22 -> 43550.798
A26: Enterprise Value (in Crores) | B26: =B24+B25 -> 58276.502
A27: Less: Net Debt (in Crores) | B27: =- $B$8 -> -947
A28: Equity Value | B28: =B26+B27 -> 57329.502
A29: Shares Outstanding | B29: =$B$6 -> 95.92
A30: Intrinsic Value per Share | B30: =B28 / B29 -> 597.68038
A31: Current Market Price | B31: =$B$7 -> 2430
A32: Upside/Downside | B32: =(B30-B31)/B31 -> -0.754041

Sheet Sensitivity
A1: ASIAN PAINTS
A2: WACC inputs | H2: WACC input | I2: 0.12
A3: Terminal Growth Rate | H3: Terminat Growth Rate | I3: 0.04
A4: ='Discounted Cash Flow'!B30 -> 597.68038 | B4: 0.1 | C4: 0.11 | D4: 0.12 | E4: 0.13 | F4: 0.14
A5: 0.03 | B5: 702.83368 | C5: 613.11521 | D5: 543.3517 | E5: 487.55603 | F5: 441.91823
A6: 0.04 | B6: 801.14156 | C6: 684.87129 | D6: 597.68038 | E6: 529.87527 | F6: 475.63986
A7: 0.05 | B7: 938.7726 | C7: 780.54607 | D7: 667.53153 | E7: 582.77432 | F7: 516.85517
A8: 0.06 | B8: 1145.2192 | C8: 914.49076 | D8: 760.66641 | E8: 650.78738 | F8: 568.37431
A9: 0.07 | B9: 1489.2967 | C9: 1115.4078 | D9: 891.05523 | E9: 741.47146 | F9: 634.61321

Sheet Charts
